README.md
setup.py
hetu/__init__.py
hetu.egg-info/PKG-INFO
hetu.egg-info/SOURCES.txt
hetu.egg-info/dependency_links.txt
hetu.egg-info/requires.txt
hetu.egg-info/top_level.txt
hetu/common/__init__.py
hetu/common/counter.py
hetu/common/module.py
hetu/core/__init__.py